{"blog_github_github-ssh-key.md":"CFQQoqVU","blog_github_deploy.md":"CuVj374w","blog_python_pipenv.md":"CiI0GIFj","blog_python_smtp.md":"CEAWrkPV","blog_index.md":"N06-K6iY","design-pattern_singleton.md":"v751HNOm","blog_linux_scp.md":"C1R3w8TG","spring_aop_logging.md":"Blibz66A","design-pattern_factory.md":"DMGQIeaH","blog_python_pyqt5-gui.md":"DVDMoC1N","blog_rttov_rttov.md":"DVmyMZSX","design-pattern_index.md":"1FFIvG0B","design-pattern_builder.md":"BorzBRM8","blog_rttov_rttov-centos.md":"DG7OmydF","spring_admin.md":"hFiXh_fJ","spring_advice_exception.md":"Cjbj7_zd","spring_advice_response.md":"C6L11hrj","spring_result.md":"DrzEsVGF","spring_log.md":"CnVYmBZc","design-pattern_spring-strategy.md":"DLjwh_bs","index.md":"CHSZ-ort","spring_controller_test.md":"DCkduTcJ","kotlin_ch01.md":"CPZePGeu"}
